haybox_cli/__init__.py
haybox_cli/main.py
haybox_cli-0.1.5.dist-info/METADATA
haybox_cli-0.1.5.dist-info/WHEEL
haybox_cli-0.1.5.dist-info/entry_points.txt
haybox_cli-0.1.5.dist-info/RECORD
