Metadata-Version: 2.3
Name: haybox-cli
Version: 0.1.5
Summary: Command line app for interacting with HayBox firmware
License: GPL-3.0-only
Author: Jonathan Haylett
Author-email: jonathan@haylett.dev
Requires-Python: >=3.9,<4.0
Classifier: License :: OSI Approved :: GNU General Public License v3 (GPLv3)
Classifier: Programming Language :: Python :: 3
Classifier: Programming Language :: Python :: 3.9
Classifier: Programming Language :: Python :: 3.10
Classifier: Programming Language :: Python :: 3.11
Classifier: Programming Language :: Python :: 3.12
Classifier: Programming Language :: Python :: 3.13
Requires-Dist: click (>=8.1.7,<9.0.0)
Requires-Dist: haybox (==0.1.5)
